fs_s3fs/__init__.py
fs_s3fs/_s3fs.py
fs_s3fs/_version.py
fs_s3fs/opener.py
fs_s3fs_forked-1.1.3.dist-info/LICENSE
fs_s3fs_forked-1.1.3.dist-info/METADATA
fs_s3fs_forked-1.1.3.dist-info/WHEEL
fs_s3fs_forked-1.1.3.dist-info/entry_points.txt
fs_s3fs_forked-1.1.3.dist-info/top_level.txt
fs_s3fs_forked-1.1.3.dist-info/RECORD
