Metadata-Version: 2.1
Name: fs-s3fs-forked
Version: 1.1.3
Summary: Amazon S3 filesystem for PyFilesystem2, forked from https://github.com/PyFilesystem/s3fs
Home-page: https://gitlab.com/geovisio/infra/s3fs
Author: Antoine Desbordes
Author-email: antoine.desbordes@gmail.com
License: MIT
Keywords: pyfilesystem,Amazon,s3
Platform: any
Classifier: Development Status :: 4 - Beta
Classifier: Intended Audience :: Developers
Classifier: License :: OSI Approved :: MIT License
Classifier: Operating System :: OS Independent
Classifier: Programming Language :: Python
Classifier: Programming Language :: Python :: 2.7
Classifier: Programming Language :: Python :: 3.3
Classifier: Programming Language :: Python :: 3.4
Classifier: Programming Language :: Python :: 3.5
Classifier: Programming Language :: Python :: 3.6
Classifier: Programming Language :: Python :: 3.7
Classifier: Topic :: System :: Filesystems
License-File: LICENSE
Requires-Dist: boto3 (~=1.9)
Requires-Dist: fs (~=2.4)
Requires-Dist: six (~=1.10)
